{
  "slug": "bain-froid",
  "titre": "Top 10 baignoires et tonneaux bain froid 2026 : comparatif",
  "extrait": "Tonneau en bois, cuve gonflable ou baignoire avec chiller ? On compare les 10 meilleures solutions bain froid maison 2026 — prix, isolation, facilité d'entretien et efficacité réelle pour la récupération.",
  "complement": "bain-froid",
  "objectif": "Récupération sportive",
  "type": "comparatif",
  "duree": "8 min",
  "date": "2026-06-16",
  "updated": "2026-06-16",
  "marque_produit": "JOLT Recovery",
  "marque_lien": "https://getjolt.fr",
  "marque_description": "spécialiste des appareils de récupération sportive — bains froids, bottes de compression et pistolets de massage",
  "contenu_html": "<div class='verdict-rapide'><div class='verdict-rapide__header'><span class='verdict-rapide__icon'>✓</span><span class='verdict-rapide__label'>Bain froid maison : notre verdict 2026</span></div><p class='verdict-rapide__top'>Meilleur sans chiller : <strong>Ice Barrel 300</strong> — ★★★★☆ — ~900€</p><p class='verdict-rapide__top' style='margin-top:.5rem'>Meilleur avec chiller : <strong>Plunge PRO</strong> — ★★★★★ — ~3 000€</p><p class='verdict-rapide__text'>Le facteur décisif : avez-vous besoin d'un <strong>chiller (refroidisseur actif)</strong> ? Sans chiller, vous devez ajouter de la glace manuellement. Avec chiller, l'eau reste à température constante automatiquement — indispensable pour un usage quotidien sans contrainte.</p></div>\n\n<h2>1. Quel type de bain froid choisir selon votre situation ?</h2>\n<figure style='margin:1.5rem 0;border-radius:12px;overflow:hidden'><img src='https://images.pexels.com/photos/3737586/pexels-photo-3737586.jpeg?auto=compress&cs=tinysrgb&w=900&h=380&fit=crop' alt='Tonneau bain froid ice bath maison jardin récupération sportive' style='width:100%;display:block' loading='lazy'/></figure>\n<p>Il existe 4 grandes catégories d'équipements pour pratiquer le bain froid à domicile, avec des prix et contraintes très différents :</p>\n<div style='overflow-x:auto;margin:1.5rem 0'><table style='width:100%;border-collapse:collapse;font-size:.88rem'>\n<thead><tr style='background:#1E293B;color:#fff'><th style='padding:.7rem 1rem;text-align:left'>Type</th><th style='padding:.7rem 1rem'>Prix</th><th style='padding:.7rem 1rem'>Entretien</th><th style='padding:.7rem 1rem'>Idéal pour</th></tr></thead>\n<tbody>\n<tr style='background:#F0FDF4'><td style='padding:.7rem 1rem;font-weight:700'>Gonflable / tub souple</td><td style='padding:.7rem 1rem'>100–400€</td><td style='padding:.7rem 1rem'>Facile, rangement</td><td style='padding:.7rem 1rem'>Débutants, appartement, budget serré</td></tr>\n<tr><td style='padding:.7rem 1rem;font-weight:700'>Baignoire rigide (plastique)</td><td style='padding:.7rem 1rem'>300–1 500€</td><td style='padding:.7rem 1rem'>Moyen</td><td style='padding:.7rem 1rem'>Jardin, usage régulier sans chiller</td></tr>\n<tr style='background:#F8FAFC'><td style='padding:.7rem 1rem;font-weight:700'>Cuve + chiller intégré</td><td style='padding:.7rem 1rem'>2 000–5 000€</td><td style='padding:.7rem 1rem'>Faible (auto)</td><td style='padding:.7rem 1rem'>Usage quotidien, athlètes confirmés</td></tr>\n<tr><td style='padding:.7rem 1rem;font-weight:700'>Tonneau bois</td><td style='padding:.7rem 1rem'>500–2 000€</td><td style='padding:.7rem 1rem'>Plus complexe</td><td style='padding:.7rem 1rem'>Esthétique, extérieur, prestige</td></tr>\n</tbody></table></div>\n<p>Le coût d'exploitation aussi compte : sans chiller, vous avez besoin de 5–10 kg de glace par session en été (~2–3€/session), soit ~50–90€/mois si vous pratiquez quotidiennement. Un chiller s'amortit rapidement.</p>\n<div class='callout-retenir'><strong>À retenir</strong> — Critères d'achat par ordre d'importance : <strong>capacité de refroidissement</strong> (atteint-il 10–15°C ?), <strong>facilité d'entretien de l'eau</strong> (filtration, traitement), <strong>isolation</strong> (conserve la température), <strong>encombrement</strong> et <strong>facilité d'entrée/sortie</strong>. La sécurité aussi : bords non glissants et stabilité.</div>\n\n<h2>2. Top 10 des meilleures solutions bain froid 2026</h2>\n<div style='overflow-x:auto;margin:1.5rem 0'>\n<table class='cg-products-table'>\n  <thead><tr><th>#</th><th>Produit</th><th>Note</th><th>Prix</th><th>Points forts</th><th>Pour qui</th></tr></thead>\n  <tbody>\n    <tr class='cg-products-table__top'>\n      <td><span class='cg-num cg-num--1'>1</span></td>\n      <td><strong>Plunge PRO</strong><br/><span class='cg-tag'>Meilleur avec chiller</span></td>\n      <td><span class='cg-stars'>★★★★★</span></td>\n      <td><strong>~3 000€</strong></td>\n      <td>Chiller jusqu'à 3°C · filtre UV+ozone · 560 L · usage int./ext.</td>\n      <td>Athlètes, usage quotidien</td>\n    </tr>\n    <tr>\n      <td><span class='cg-num cg-num--2'>2</span></td>\n      <td><strong>Ice Barrel 400</strong><br/><span class='cg-tag'>Meilleur sans chiller</span></td>\n      <td><span class='cg-stars'>★★★★<span class='cg-star-empty'>★</span></span></td>\n      <td>~1 200€</td>\n      <td>Polypropylène robuste · couvercle · 113 L · assise intégrée</td>\n      <td>Usage régulier extérieur</td>\n    </tr>\n    <tr>\n      <td><span class='cg-num cg-num--2'>3</span></td>\n      <td><strong>Ice Barrel 300</strong></td>\n      <td><span class='cg-stars'>★★★★<span class='cg-star-empty'>★</span></span></td>\n      <td>~900€</td>\n      <td>Version compacte · même qualité Ice Barrel · idéal petits espaces</td>\n      <td>Terrasse, intérieur spacieux</td>\n    </tr>\n    <tr>\n      <td><span class='cg-num cg-num--2'>4</span></td>\n      <td><strong>JOLT Ice Bath Pro</strong></td>\n      <td><span class='cg-stars'>★★★★<span class='cg-star-empty'>★</span></span></td>\n      <td>~400€</td>\n      <td>Gonflable 180 L · isolation 4 couches · couvercle + pompe · SAV FR</td>\n      <td>Polyvalent, SAV France</td>\n    </tr>\n    <tr style='background:#F8FAFC'>\n      <td><span class='cg-num cg-num--2'>5</span></td>\n      <td><strong>The Cold Pod Ultimate</strong></td>\n      <td><span class='cg-stars'>★★★★<span class='cg-star-empty'>★</span></span></td>\n      <td>~180€</td>\n      <td>Gonflable · 5 couches isolation · bestseller · léger · rangement</td>\n      <td>Appartement, budget serré</td>\n    </tr>\n    <tr>\n      <td><span class='cg-num'>6</span></td>\n      <td><strong>Brass Monkey Original</strong></td>\n      <td><span class='cg-stars'>★★★★<span class='cg-star-empty'>★</span></span></td>\n      <td>~1 500€</td>\n      <td>Chiller jusqu'à 7°C · acier inox 304 · design premium · durable</td>\n      <td>Haut de gamme accessible</td>\n    </tr>\n    <tr style='background:#F8FAFC'>\n      <td><span class='cg-num'>7</span></td>\n      <td><strong>Renu Therapy Cold Rush</strong></td>\n      <td><span class='cg-stars'>★★★★<span class='cg-star-empty'>★</span></span></td>\n      <td>~2 500€</td>\n      <td>Chiller silencieux · usage intérieur · filtration avancée</td>\n      <td>Usage intérieur, appart. haut de gamme</td>\n    </tr>\n    <tr>\n      <td><span class='cg-num'>8</span></td>\n      <td><strong>Tonneau en cèdre Custom (artisan)</strong></td>\n      <td><span class='cg-stars'>★★★★<span class='cg-star-empty'>★</span></span></td>\n      <td>600–2 000€</td>\n      <td>Esthétique · naturel · sur mesure · sans plastique · durable</td>\n      <td>Amateur de bois, jardin, esthétique</td>\n    </tr>\n    <tr style='background:#F8FAFC'>\n      <td><span class='cg-num'>9</span></td>\n      <td><strong>Sun Home Saunas Cold Plunge Pro</strong></td>\n      <td><span class='cg-stars'>★★★<span class='cg-star-empty'>★★</span></span></td>\n      <td>~1 800€</td>\n      <td>Chiller · pensé pour combo sauna · bonne finition</td>\n      <td>Combo chaud-froid maison</td>\n    </tr>\n    <tr>\n      <td><span class='cg-num'>10</span></td>\n      <td><strong>Baignoire standard (DIY)</strong></td>\n      <td><span class='cg-stars'>★★★<span class='cg-star-empty'>★★</span></span></td>\n      <td>0€</td>\n      <td>Immédiat · suffisant · 10 kg de glace = 12–14°C · pour tester</td>\n      <td>Débutants absolus, test protocole</td>\n    </tr>\n  </tbody>\n</table>\n</div>\n\n<h2>3. Comment entretenir l'eau de son bain froid ?</h2>\n<figure style='margin:1.5rem 0;border-radius:12px;overflow:hidden'><img src='https://images.pexels.com/photos/3864434/pexels-photo-3864434.jpeg?auto=compress&cs=tinysrgb&w=900&h=340&fit=crop' alt='Entretien bain froid eau filtration hygiène' style='width:100%;display:block' loading='lazy'/></figure>\n<p>L'entretien de l'eau est crucial pour éviter la prolifération bactérienne (légionellose, infections cutanées). Sans chiller/filtration : <strong>changez l'eau toutes les 2–3 utilisations</strong> maximum. Avec système de filtration :</p>\n<div style='overflow-x:auto;margin:1.5rem 0'><table style='width:100%;border-collapse:collapse;font-size:.88rem'>\n<thead><tr style='background:#1E293B;color:#fff'><th style='padding:.7rem 1rem'>Traitement</th><th style='padding:.7rem 1rem'>Fréquence</th><th style='padding:.7rem 1rem'>Produit</th><th style='padding:.7rem 1rem'>Remarque</th></tr></thead>\n<tbody>\n<tr style='background:#F0FDF4'><td style='padding:.7rem 1rem;font-weight:700'>Désinfection</td><td style='padding:.7rem 1rem'>Après chaque session</td><td style='padding:.7rem 1rem'>50 ml eau oxygénée 3%</td><td style='padding:.7rem 1rem'>Ou UV si équipé</td></tr>\n<tr><td style='padding:.7rem 1rem;font-weight:700'>Équilibre pH</td><td style='padding:.7rem 1rem'>2x/semaine</td><td style='padding:.7rem 1rem'>pH test + correcteur</td><td style='padding:.7rem 1rem'>Cible : pH 7,2–7,6</td></tr>\n<tr style='background:#F8FAFC'><td style='padding:.7rem 1rem;font-weight:700'>Changement eau</td><td style='padding:.7rem 1rem'>Mensuel (avec filtre)</td><td style='padding:.7rem 1rem'>—</td><td style='padding:.7rem 1rem'>Toutes les 2–3 sessions (sans filtre)</td></tr>\n</tbody></table></div>\n<div class='callout-conseil'><strong>💡 Douche avant le bain</strong> — Toujours doucher avant d'entrer dans le bain froid, sans savon (le savon dégrade le traitement de l'eau). Cette simple règle multiplie par 5 la durée de vie de l'eau sans renouvellement.</div>\n\n<h2>FAQ</h2>\n<details><summary>Combien de kg de glace pour atteindre 12°C dans une baignoire ?</summary><p>Pour une baignoire standard (~200 L) à 20°C : comptez <strong>10–12 kg de glace</strong> pour descendre à 12°C. Par temps chaud (+25°C), ajoutez 3–4 kg. La température remonte d'~1–2°C toutes les 5 minutes dans une baignoire non isolée. Un Ice Barrel ou tub isolé conserve la température 2 à 3 fois plus longtemps.</p></details>\n<details><summary>Quelle différence entre bain froid et cryothérapie corps entier en chambre ?</summary><p>La <a href='/articles/cryotherapie'>chambre de cryothérapie</a> (–110°C) refroidit la peau en 3 minutes sans refroidir les organes internes. Le bain froid (10–15°C) refroidit les tissus musculaires en profondeur sur 10–15 minutes. Pour la récupération musculaire, l'immersion est légèrement plus efficace. Pour les effets neurochimiques (dopamine, noradrénaline) et l'accessibilité, les deux sont équivalents. Le bain froid est nettement moins cher.</p></details>\n<details><summary>Un bain froid peut-il aider à perdre du poids ?</summary><p>Marginalement. L'exposition au froid active le tissu adipeux brun (BAT) qui brûle des calories pour maintenir la température corporelle. Des études montrent une augmentation du métabolisme de 10–15% pendant 1–2h après l'immersion. Sur l'année, cela représente quelques kilos. Ce n'est pas une méthode de perte de poids principale, mais un bonus dans une routine globale.</p></details>\n<details><summary>Y a-t-il des contre-indications au bain froid ?</summary><p>Oui : maladie cardiovasculaire non contrôlée, hypertension sévère, syndrome de Raynaud, grossesse. Ne jamais pratiquer seul les premières fois. Sortez immédiatement si vous ressentez douleur thoracique, vertiges ou engourdissement des membres. Les personnes âgées doivent rester sous surveillance au début. Commencez toujours par 18–20°C pour conditionner votre système nerveux.</p></details>"
}
